weather_info_yb2503/__init__.py
weather_info_yb2503/weather_info_yb2503.py
weather_info_yb2503-0.1.0.dist-info/LICENSE
weather_info_yb2503-0.1.0.dist-info/WHEEL
weather_info_yb2503-0.1.0.dist-info/METADATA
weather_info_yb2503-0.1.0.dist-info/RECORD
