Metadata-Version: 2.1
Name: weather-info-yb2503
Version: 0.1.0
Summary: weather_info_yb2503 will provide convenient weather infomation providing service with simple functions. 
Home-page: https://github.com/QMSS-G5072-2021/yb2503
License: MIT
Author: Yunxin Bo
Requires-Python: >=3.8,<4.0
Classifier: License :: OSI Approved :: MIT License
Classifier: Programming Language :: Python :: 3
Classifier: Programming Language :: Python :: 3.8
Classifier: Programming Language :: Python :: 3.9
Project-URL: Repository, https://github.com/QMSS-G5072-2021/yb2503
